[
  {
    "brand": "Geek Bar",
    "title": "RIA NV30K Disposable Vape By Geek Bar",
    "price": "$56.60",
    "link": "https://vaperanger.com/products/ria-nv30k-disposable-vape-by-geek-bar",
    "image_url": "https://cdn11.bigcommerce.com/s-hqim8tz8ly/images/stencil/380x380/products/72555/119856/1__47102.1739971718.jpg?c=2",
    "description": "The RIA NV30K Disposable Vape by Geek Bar stands out with a 1000mAh rechargeable battery, dual mesh coils, and a max output of 35W for powerful, flavorful clouds. Its premium leather design adds a touch of class, while the light on/off function offers convenience. With 15ml of e-liquid and 30,000 puffs, this vape is ideal for both long-term enjoyment and immediate satisfaction.\nRIA NV30K Disposable Vape By Geek Bar Features:\n\n15mL Pre-Filled E-Liquid\n5% (50mg) Nicotine Strength\n1000mAh Type-C Rechargeable Battery\nDual Mesh Coil &amp; 35W Max Output\nPremium Leather Design with Light On/Off Function\n&nbsp;Powered by Geek Bar\n\nRIA NV30K Flavors:\n\nBlue Razz Ice &ndash; A bold burst of tangy blue raspberry with an icy cool finish.\nBlueberry Punch &ndash; Juicy blueberries meet a punch of fruity goodness in every inhale.\nCrazy Berry &ndash; A wild mix of sweet and tart berries for an electrifying vape.\nDualicious &ndash; A perfectly blended duo of fruity flavors for a smooth, satisfying experience.\nFcuking Fab &ndash; A unique fusion of flavors that&rsquo;s bold, rich, and downright fabulous.\nMiami Mint &ndash; Crisp, refreshing mint with a smooth, cooling sensation.\nPeach Gummy &ndash; Sweet, chewy peach candy flavor with a juicy finish.\nPineapple Lime &ndash; Tropical pineapple meets zesty lime for a tangy-sweet delight.\nSour Strawberry Dragon &ndash; Tart strawberry with a fiery dragon fruit twist.\nWatermelon B-Pop &ndash; A nostalgic watermelon candy with a fizzy pop of sweetness.\nWatermelon Ice &ndash; Refreshing watermelon with an exhilarating icy blast.\n\nRIA NV30K Wholesale:\nThe RIA NV30K Disposable Vape By Geek Bar Wholesale is a premium, high-volume option with 30,000 puffs, dual mesh coils, and a sleek leather finish. Perfect for retailers looking to offer cutting-edge vaping technology and exceptional value.\nLearn More: Geek Bar Products &amp; Industry Trends\n\nBest Geek Bar Flavors in 2025: A Comprehensive Guide\nThe New From Geek Bar: Geek Bar RIA NV30K Vape: Redefining Power, Flavor, and Innovation\nThe Evolution of Geek Bar From Early Models to the Geek Bar Pulse X and Geek Bar SKYVIEW",
    "stock_status": "Sold Out",
    "model_type": "RIA NV30K",
    "flavors": [
      "Blue Razz Ice",
      "Blueberry Punch",
      "Crazy Berry",
      "Dualicious",
      "Fcuking Fab",
      "Miami Mint",
      "Peach Gummy",
      "Pineapple Lime",
      "Sour Strawberry Dragon",
      "Watermelon B-Pop",
      "Watermelon Ice",
      "Pink Raz Lemonade"
    ],
    "puff_count": 30000,
    "nicotine_strength": "5% (50mg)",
    "battery_capacity": "1000mAh",
    "coil_type": "Dual Mesh",
    "e_liquid_capacity": "15ml"
  },
  {
    "brand": "Geek Bar",
    "title": "Geek Bar Pulse X Vape 25K",
    "price": "$58.00",
    "link": "https://vaperanger.com/products/geek-bar-pulse-x-vape",
    "image_url": "https://cdn11.bigcommerce.com/s-hqim8tz8ly/images/stencil/380x380/products/71084/119366/Geek_Bar_Pulse_X_Vape_25K_18__11337.1738104040.jpg?c=2",
    "description": "Maximum Purchase Quantity 3 x 5-Packs. Attract customers with the Geek Bar Pulse X Vape. Featuring up to 25,000 puffs, an 18mL e-liquid capacity, and an 820mAh rechargeable battery, this vape delivers exceptional flavor and performance. Dual mesh coils and a 3D curved screen enhance the experience, making it a wholesale essential.\nGeek Bar Pulse X Vape Features:\n\nDisplay Box Count: 5\n18mL Pre-Filled E-Liquid\n5% (50mg) Nicotine Strength\n820mAh Type-C Rechargeable Battery\nTwo Vaping Modes: Regular Mode (~25,000 Puffs), Pulse Mode (~15,000 Puffs)\nDual Mesh Coil\n3D Curved Screen with Starry UI\nCharges at 1.5A, Supports Voltage Range 5-20V\nDual Core Heating\n\nGeek Bar Pulse X Vape Flavors:\n\nBanana Taffy Freeze: Creamy banana taffy with a cool finish.\nBlackberry B-Pop: Juicy blackberries with a sweet candy twist.\nBlue Rancher: A bold blend of blue raspberry and sweet candy.\nBlue Razz Ice: Tart blue raspberry with a refreshing icy hit.\nGrapefruit Refresher: Tangy grapefruit with a crisp, refreshing edge.\nLemon Heads: Zesty lemon paired with sweet, tangy candy bits.\nLime Berry Orange: A citrus medley of lime, berry, and orange.\nMiami Mint: Cool and invigorating mint flavor.\nOrange Fcuking Fab: Bold and juicy orange explosion.\nRaspberry Peach Lime: A fruity fusion of raspberry, peach, and lime.\nSour Apple Ice: Tart green apple with an icy blast.\nSour Fcuking Fab: Intense sour candy flavor.\nSour Mango Pineapple: Tangy mango with a sweet pineapple twist.\nStrawberry B-Pop: Sweet strawberries with a pop of candy.\nWatermelon Ice: Refreshing watermelon with a cool finish.\nSour Straws: Tangy fruity delight.\nBlackberry Blueberry: Bold berry fusion.\nStrawberry Colada: Tropical berry twist.\nWhite Peach Raspberry: Juicy peach blend.\nCool Mint: Refreshing mint breeze.\n\nPink and Blue: A sweet, tangy blend of pink berries and blue candy for a vibrant flavor burst.\n\n\nStrawberry Kiwi Ice: Juicy strawberry and tart kiwi with an icy menthol finish for a refreshing kick.\n\n\nATL Mint: Crisp, bold mint flavor with a cool and refreshing finish.\n\n\nOrange Dragon: Zesty orange meets exotic dragon fruit for a tangy, tropical blend.\n\n\nStrawberry Watermelon: A juicy mix of sweet strawberries and refreshing watermelon for a fruity delight.\n\n\nGeek Bar Pulse X Vape Wholesale:\nGeek Bar Pulse X Vape offers convenience and versatility in one sleek device. With its pre-filled e-liquid, rechargeable battery, and dual vaping modes, it's perfect for customers who demand performance without compromise.\nBuy Geek Bar Pulse X and Geek Bar Flavors Retail\nFrequently Asked Questions (FAQ) Geek Bar Pulse X Vape 25K\n\n\nWhat makes the Geek Bar Pulse X Vape stand out?The Geek Bar Pulse X Vape offers up to 25,000 puffs, an 18mL e-liquid capacity, and a dual-mode system, providing both regular and pulse vaping modes. Its advanced features, including dual mesh coils, a 3D curved screen, and an 820mAh rechargeable battery, make it a top choice for high-demand customers.\n\n\nHow many puffs does the Geek Bar Pulse X provide?The Geek Bar Pulse X offers up to 25,000 puffs in regular mode and around 15,000 puffs in pulse mode, making it one of the longest-lasting disposable vapes on the market.\n\n\nWhat are the available flavors for the Geek Bar Pulse X?The Geek Bar Pulse X comes in a variety of flavors, including popular options like Banana Taffy Freeze, Blue Razz Ice, Grapefruit Refresher, and many more. For a full list, you can explore flavors like Blackberry B-Pop, Lemon Heads, and Miami Mint.\n\n\nWhy should retailers stock the Geek Bar Pulse X?With its extensive puff count, premium flavor options, and innovative features like a 3D curved screen and dual mesh coils, the Geek Bar Pulse X is a must-have for vape shops looking to attract customers seeking quality and longevity in their vaping experience.\n\n\nHow is the Geek Bar Pulse X Vape packaged for wholesale?The Geek Bar Pulse X comes in a display box with a count of 5 units per box, making it convenient for retail display and inventory managementâ€¦",
    "stock_status": "Sold Out",
    "model_type": "Pulse X Vape 25K",
    "flavors": [
      "Banana Taffy Freeze",
      "Blackberry B-Pop",
      "Blue Rancher",
      "Blue Razz Ice",
      "Grapefruit Refresher",
      "Lemon Heads",
      "Lime Berry Orange",
      "Miami Mint",
      "Orange Fcuking Fab",
      "Raspberry Peach Lime",
      "Sour Apple Ice",
      "Sour Fcuking Fab",
      "Sour Mango Pineapple",
      "Strawberry B-Pop",
      "Watermelon Ice",
      "Sour Straws",
      "Blackberry Blueberry",
      "Strawberry Colada",
      "White Peach Raspberry",
      "Pink and Blue",
      "Strawberry Kiwi Ice",
      "ATL Mint",
      "Orange Dragon",
      "Strawberry Watermelon",
      "Peach (Slush Edition)",
      "Cola (Slush Edition)",
      "Wild Cherry (Slush Edition)",
      "Orange (Slush Edition)",
      "Grape (Slush Edition)",
      "Strawberry (Jam Edition)",
      "Blueberry (Jam Edition)",
      "Peach (Jam Edition)",
      "Orange (Jam Edition)",
      "Raspberry (Jam Edition)"
    ],
    "puff_count": 25000,
    "nicotine_strength": "5%",
    "battery_capacity": "820mAh",
    "coil_type": "Dual Mesh",
    "e_liquid_capacity": "18mL"
  },
  {
    "brand": "RAZ",
    "title": "RAZ DC25000 Vape",
    "price": "$50.00",
    "link": "https://vaperanger.com/products/raz-dc25000-vape",
    "image_url": "https://cdn11.bigcommerce.com/s-hqim8tz8ly/images/stencil/380x380/products/70982/119759/VR__60085__84537__48129.1739215672.jpg?c=2",
    "description": "LIMIT 10 PIECES PER FLAVOR PER CUSTOMER. Introducing the RAZ DC25000 Disposable Vape (Raz LTX 25K Disposable), designed for vape shop owners seeking top-tier wholesale products. With 25000 puffs, 5% nicotine strength, and 16ml e-liquid capacity, it offers long-lasting satisfaction. Featuring an 800mAh battery, USB Type-C charging, adjustable airflow, full display screen, e-liquid level indicator, and integrated mesh coil, it's the epitome of convenience and performance for discerning vape enthusiasts.\n\n\n\n\nRAZ DC25000 Disposable Vape (Raz LTX 25K Disposable) Features:&nbsp;\n\n\nLong-lasting Puffs: Enjoy up to 25000 or 25K puffs with the RAZ DC25000, ensuring extended vaping sessions without the need for frequent replacements. Ideal for heavy users or those who prefer uninterrupted enjoyment.\n\n\nPowerful Nicotine Delivery: Experience a satisfying nicotine hit with a 5% (50mg) nicotine level in each puff of the RAZ DC25000. Perfect for users seeking a potent vaping experience that closely mimics traditional smoking.\n\n\nGenerous E-Liquid Capacity: With a spacious 16ml e-liquid reservoir, the RAZ DC25000 ensures prolonged vaping enjoyment without the hassle of frequent refills. Ideal for users who value convenience and extended usage between refills.\n\n\nHigh-capacity Battery: Equipped with an 800mAh battery, the RAZ DC25000 provides ample power to support long vaping sessions. Enjoy reliable performance throughout the day without worrying about running out of battery.\n\n\nConvenient USB Type-C Charging: The USB Type-C charging port of the RAZ DC25000 allows for quick and hassle-free recharging. Enjoy the convenience of fast charging, ensuring minimal downtime between vaping sessions.\n\n\nAdjustable Airflow: Tailor your vaping experience to your preferences with the adjustable airflow feature of the RAZ DC25000. Customize the airflow to achieve the perfect balance of vapor production and flavor intensity for a personalized vaping experience.\n\n\nFull Display Screen: Stay informed about your vaping settings and battery life with the full display screen of the RAZ DC25000. Easily monitor important information at a glance for enhanced convenience and control.\n\n\nE-Liquid Level Indicator: Keep track of your e-liquid level with the built-in indicator of the RAZ DC25000. Never be caught off guard by low e-liquid levels again, ensuring you're always ready for uninterrupted vaping enjoyment.\n\n\nIntegrated Mesh Coil: Experience smooth and flavorful vapor production with the integrated mesh coil of the RAZ DC25000. Enjoy consistent heating and enhanced flavor delivery for a satisfying vaping experience with every puff.\n\n\nRAZ DC25000 Flavors:\n\n&nbsp;\nBanana Candy &ndash; A sweet, candy-like banana flavor for a fun vape.\nBangin' Sour Berries &ndash; A burst of tangy sour berries for a bold vape.\nBlack Cherry Peach &ndash; Lush black cherries paired with smooth peach.\nBlack&amp;Blue Lime &ndash; A blend of blackberries, blueberries, and zesty lime.\nBlue Raz (Gush Edition) &ndash; A gush of bold blue raspberry flavor.\nBlueberry (Punch Edition) &ndash; Rich and tangy blueberry with a powerful punch.\nBlueberry Watermelon &ndash; A delicious fusion of juicy blueberries and watermelon.\nBlue Raz Ice &ndash; Tangy blue raspberry combined with a chilly ice sensation.\nClear &ndash; A smooth, clean vaping experience with no overpowering flavor.\nClear Diamond &ndash; A premium, subtle vape with a smooth finish.\nClear Sapphire &ndash; A refined, smooth flavor with a clean, crisp finish.\nCherry Strapple &ndash; A sweet mix of cherry and apple with a vibrant flavor.\nFire &amp; Ice &ndash; A spicy-sweet blend of heat and coolness in every puff.\nFrozen Edition - Banana &ndash; Creamy banana with a frosty coolness.\nFrozen Edition - Cherry Apple &ndash; Sweet cherry and crisp apple with an icy finish.\nFrozen Edition - Dragonfruit Lemon &ndash; Exotic dragonfruit with a tangy lemon twist.\nFrozen Edition - Juicy Strawberry &ndash; Sweet strawberries with a refreshing chill.\nFroâ€¦",
    "stock_status": "Sold Out",
    "model_type": "DC25000",
    "flavors": [
      "Banana Candy",
      "Bangin' Sour Berries",
      "Black Cherry Peach",
      "Black&Blue Lime",
      "Blue Raz (Gush Edition)",
      "Blueberry (Punch Edition)",
      "Blueberry Watermelon",
      "Blue Raz Ice",
      "Clear",
      "Clear Diamond",
      "Clear Sapphire",
      "Cherry Strapple",
      "Fire &amp; Ice",
      "Frozen Edition - Banana",
      "Frozen Edition - Cherry Apple",
      "Frozen Edition - Dragonfruit Lemon",
      "Frozen Edition - Juicy Strawberry",
      "Fro...",
      "Georgia Peach",
      "Hawaiian (Punch Edition)",
      "Ice Blue Dragon",
      "Mango Loco",
      "Miami Mint",
      "New York Mint",
      "Night Crawler",
      "Orange Berry Lime Ice",
      "Orange Mango",
      "Orange Pineapple (Punch Edition)",
      "Pink Lemonade Mint",
      "Raspberry Kiwi Pear",
      "Razzle Dazzle",
      "Rainbow Rain",
      "Sour Apple Ice",
      "Sour Apple Watermelon Peach",
      "Sour Raspberry (Punch Edition)",
      "Sour Raspberry Watermelon",
      "Strawberry Burst",
      "Strawberry Kiwi Pear",
      "Strawberry Orange Tang",
      "Strawberry Peach (Gush Edition)",
      "Tobacco",
      "Triple Berry (Gush Edition)",
      "Triple Berry (Punch Edition)",
      "Tropical (Gush Edition)",
      "Watermelon Ice",
      "White Grape (Gush Edition)"
    ],
    "puff_count": 25000,
    "nicotine_strength": "5%",
    "battery_capacity": "800mAh",
    "coil_type": "Integrated Mesh Coil",
    "e_liquid_capacity": "16ml"
  },
  {
    "brand": "Geek Bar",
    "title": "Geek Bar Pulse Vape",
    "price": "$47.00",
    "link": "https://vaperanger.com/products/geek-bar-pulse/",
    "image_url": "https://cdn11.bigcommerce.com/s-hqim8tz8ly/images/stencil/380x380/products/69321/119235/Diseno_sin_titulo__50122__13206.1738073205.jpg?c=2",
    "description": "MAX 3 CASES PER FLAVOR. Geek Bar Pulse Wholesale Disposable Vape offers vape shop owners a premium option with 15000 puffs. With two power settings - standard and pulse - and a 650mAh battery, it ensures lasting enjoyment. Each vape contains 16mL of preloaded e-liquid with a nicotine concentration of 5% (50mg). Featuring a USB Type-C charging port and a built-in dual mesh coil, it's both convenient and powerful.\nGeek Bar Pulse Vape Features:\n\nStandard Mode Maximum Puffs: Up to 15,000 for extended usage.\nPulse Mode Maximum Puffs: Up to 7,500 for a more intense vaping experience.\nNicotine Concentration: 5% (50mg) for a satisfying hit.\nPreloaded Capacity: 16mL of e-liquid for long-lasting enjoyment.\nBattery Capacity: 650mAh for reliable performance.\nUSB Type-C Charging Port: Fast and efficient recharging.\nActivation Method: Draw-Activated for easy use.\nTwo Power Settings: Standard and Pulse modes for customizable vaping experiences with the Geek Bar Pulse Vape.\nBuilt-In Dual Mesh Coil: Enhanced flavor and vapor production.\nScreen Display: Clear and informative display for easy monitoring of settings.\nBattery Status Indicator: Always know when to recharge your Geek Bar Pulse Vape.\nE-Liquid Quantity Indicator: Easily track remaining e-liquid levels for uninterrupted vaping.\n\nGeek Bar Pulse Wholesale Flavors:\n\n\nBerry Bliss: Immerse yourself in a blissful blend of assorted berries, offering a symphony of sweet and tangy flavors with every puff.\n\n\nBlack Cherry: Indulge in the rich and deep flavor of black cherries, capturing the essence of ripe fruit in every inhale.\n\n\nBlow Pop: Enjoy the nostalgic taste of your favorite childhood candy with this sweet and fruity flavor reminiscent of classic blow pops.\n\n\nBlue Mint (Scorpio): Experience the cool and refreshing taste of mint, infused with a hint of blueberry sweetness, creating a crisp and invigorating vaping sensation.\n\n\nBlueberry Watermelon: Delight in the perfect balance of sweet blueberries and juicy watermelon, offering a refreshing vaping experience that is both fruity and satisfying.\n\n\nCali Cherry: Taste the sweetness of California cherries in every puff. Enjoy the juicy burst of cherry flavor, creating a vaping experience that is both satisfying and delectable.\n\n\nCherry Bomb: Experience an explosion of cherry flavor with each inhale, offering a bold and intense vaping experience that will leave you craving more.\n\n\nCrazy Melon (Virgo): Embark on a wild ride of melon madness with this exhilarating blend of assorted melons, offering a burst of fruity sweetness with every puff.\n\n\nDragon Melon (Capricorn): Awaken your senses with the exotic flavor of dragon fruit and juicy melon, creating a unique and captivating vaping experience.\n\n\nFcuking Fab: Excite your taste buds with this fabulously flavorful blend. With a name like that, you know it's going to be an unforgettable vaping experience.\n\n\nGrape Blow Pop (Aquarius): Satisfy your sweet tooth with the nostalgic taste of grape blow pops, offering a burst of fruity sweetness with every puff.\n\n\nGrape Lemon (Gemini): Experience the perfect balance of tangy lemon and sweet grape, offering a refreshing and invigorating vaping experience that will tantalize your taste buds.\n\n\nJuicy Peach: Delight in the luscious sweetness of succulent peaches, capturing the essence of ripe fruit in every puff. Experience the juicy burst of peach flavor with each inhale, followed by a smooth and satisfying exhale.\n\n\nMeta Moon: Explore the mysterious flavor of Meta Moon, offering a unique and captivating vaping experience that will keep you coming back for more.\n\n\nMexico Mango: Transport yourself to the tropical paradise with the bold and exotic flavor of ripe mangoes from Mexico. Each puff delivers a burst of mango goodness, providing a satisfying vaping experience.\n\n\nMiami Mint: Refresh your senses with the revitalizing taste of cool mint. Each puff offers a crisp and refreshing minty flavor that invigorates your palate, leaving you feeling refreshed and eâ€¦",
    "stock_status": "Sold Out",
    "model_type": "Pulse Vape",
    "flavors": [
      "Berry Bliss",
      "Black Cherry",
      "Blow Pop",
      "Blue Mint (Scorpio)",
      "Blueberry Watermelon",
      "Cali Cherry",
      "Cherry Bomb",
      "Crazy Melon (Virgo)",
      "Dragon Melon (Capricorn)",
      "Fcuking Fab",
      "Grape Blow Pop (Aquarius)",
      "Grape Lemon (Gemini)",
      "Juicy Peach",
      "Meta Moon",
      "Mexico Mango",
      "Miami Mint",
      "OMG Blow Pop (Aries)",
      "Orange Creamsicle",
      "Pink Lemonade",
      "Sour Apple Blow Pop (Libra)",
      "Sour Blue Dust",
      "Sour Cherry Apple",
      "Sour Gush",
      "Sour Strawberry",
      "Sour Watermelon Drop",
      "Strawberry Banana",
      "Strawberry Mango",
      "Tropical Rainbow",
      "Watermelon Ice",
      "White Grape",
      "WildBerry (Savers Edition)",
      "Drop Sour (Savers Edition)"
    ],
    "puff_count": 15000,
    "nicotine_strength": "5% (50mg)",
    "battery_capacity": "650mAh",
    "coil_type": "Dual Mesh",
    "e_liquid_capacity": "16mL"
  },
  {
    "brand": "Raz",
    "title": "Raz TN9000 Vape",
    "price": "$48.43",
    "link": "https://vaperanger.com/products/raz-tn9000-disposable",
    "image_url": "https://cdn11.bigcommerce.com/s-hqim8tz8ly/images/stencil/380x380/products/69097/119305/Raz_TN9000_Disposable_Vape_-_9000_Puffs__39283__00046.1738082430.jpg?c=2",
    "description": "The Raz TN9000 vape features a sleek design and is pre-filled with 12mL of e-liquid, providing your customers with approximately 9000 puffs of pure vaping pleasure. With a robust 650mAh Type-C rechargeable battery, it ensures longevity and convenience. The adjustable airflow feature allows vapers to tailor their experience of RAZ TN9000 flavors. Offering a nicotine strength of 5% (50mg), it caters to both beginner and experienced vapers. \nRaz TN9000 Vape Features:\n\n12mL Pre-Filled E-Liquid.\n5% (50mg) Nicotine Strength.\n650mAh Type-C Rechargeable Battery .\nApproximately 9000 Puffs.\nAdjustable Airflow.\n\nRaz TN9000 Vape Flavors:\n\n\nNEW Dream Edition Violet: Grape sweetness meets delicate strawberries in a tantalizing vape blend.\n\n\nNEW Dream Edition Ruby: Cherries, strawberries, raspberries unite for a vibrant, party-worthy vape.\n\n\nNEW Dream Edition Vicky: Zesty Pink Lemonade: tart lemons with a pinch of sugar.\n\n\nNEW Dream Edition Tiffany: Tropical Kiwi Watermelon: sweet kiwis collide with juicy watermelon.\n\n\nBanana Coconut: Transport yourself to a tropical paradise with the exotic blend of ripe bananas and creamy coconut, offering a delightful vaping experience that is both smooth and satisfying.\n\n\nBlue Razz Cotton Cloudz: Indulge in the sweet and airy taste of blue raspberry cotton candy, reminiscent of carnival days and childhood memories.\n\n\nBlue Raz Ice: Immerse yourself in the invigorating blend of tangy blue raspberry infused with a chilling menthol breeze. Each puff delivers a refreshing burst of fruity sweetness followed by a cool exhale, leaving your palate revitalized and craving more.\n\n\nCherry Lemon: Treat your taste buds to the delightful fusion of ripe cherries and zesty lemons. With each inhale, experience the harmonious balance of sweet and tangy notes, creating a mouthwatering sensation that tantalizes the senses and leaves you feeling refreshed.\n\n\nCitronnade: Refresh your senses with the zesty and invigorating taste of citronnade, offering a burst of citrusy goodness with every puff.\n\n\nDragon Fruit Lemon: Experience the exotic flavor of dragon fruit combined with the zesty kick of lemon, creating a unique and refreshing vaping experience that will awaken your senses.\n\n\nGeorgia Peach: Delight in the luscious sweetness of Georgia peaches, capturing the essence of ripe fruit in every puff. Experience the juicy burst of peach flavor with each inhale, followed by a smooth and satisfying exhale.\n\n\nGrape Ice: Experience the bold and juicy flavor of sun-ripened grapes, perfectly complemented by a refreshing menthol twist. Each inhale delivers a burst of grape goodness, while the exhale leaves behind a cool sensation, creating a revitalizing vaping experience that is both satisfying and invigorating.\n\n\nGraham Twist: Indulge in the warm and comforting taste of graham crackers, offering a hint of sweetness and a touch of nostalgia with every puff.\n\n\nMango Colada: Transport yourself to a tropical island getaway with the exotic blend of ripe mangoes and creamy coconut, offering a smooth and satisfying vaping experience.\n\n\nMiami Mint: Transport yourself to the vibrant city of Miami with the revitalizing taste of cool mint. Refresh your senses with each puff as the crisp minty flavor invigorates your palate, leaving you feeling refreshed and energized, making it the perfect choice for a hot summer day.\n\n\nNight Crawler: Embark on a nighttime adventure with this mysterious and captivating flavor. Each puff offers a blend of rich and complex notes, creating an unforgettable vaping experience.\n\n\nOrange Raspberry: Savor the delightful combination of tangy oranges and sweet raspberries in this refreshing blend. It's a burst of fruity goodness that will tantalize your taste buds with every inhale.\n\n\nPeach Grapefruit: Experience the perfect balance of juicy peaches and tangy grapefruits in this flavorful blend. It's a refreshing and invigorating vaping experience that will leave you craving more.\n\n\nPineapple Passionfruit Guava: Transportâ€¦",
    "stock_status": "Sold Out",
    "model_type": "TN9000",
    "flavors": [
      "NEW Dream Edition Violet",
      "NEW Dream Edition Ruby",
      "NEW Dream Edition Vicky",
      "Banana Coconut",
      "Blue Razz Cotton Cloudz",
      "Blue Raz Ice",
      "Cherry Lemon",
      "Citronnade",
      "Dragon Fruit Lemon",
      "Georgia Peach",
      "Grape Ice",
      "Graham Twist",
      "Mango Colada",
      "Miami Mint",
      "Night Crawler",
      "Orange Raspberry",
      "Peach Grapefruit",
      "Pineapple Passionfruit Guava",
      "Strawberry Ice",
      "Strawberry Orange Mango",
      "Tiffany",
      "Triple Berry",
      "Vicky",
      "White Gummy Watermelon",
      "White Yummy Grape"
    ],
    "puff_count": 9000,
    "nicotine_strength": "5% (50mg)",
    "battery_capacity": "650mAh Type-C Rechargeable Battery",
    "coil_type": null,
    "e_liquid_capacity": "12mL Pre-Filled E-Liquid"
  },
  {
    "brand": "Lost Mary",
    "title": "Lost Mary MT15000 Turbo",
    "price": "$50.00",
    "link": "https://vaperanger.com/products/lost-mary-mt15000-turbo/",
    "image_url": "https://cdn11.bigcommerce.com/s-hqim8tz8ly/images/stencil/380x380/products/70446/103962/Lost_Mary_MT15000_Turbo_Disposable_Vape_-_15000_Puffs__63388.1713293047.jpg?c=2",
    "description": "Introducing Lost Mary MT15000 Turbo wholesale. Boasting 15000 puffs and powered by a 5% (50MG) nicotine concentration, this device offers a smooth mode at 11W and a turbo mode at 22W. Rechargeable via USB-C, it features innovative dual mesh coil technology for a premium vaping experience.\nLost Mary MT15000 Turbo Vape Features:\n\nNicotine: 5% (50MG)\nBattery Power: 11W for smooth mode, 22W for turbo mode\nPuff Count: 15000 puffs\nRechargeable: USB-C port for quick charging\nInnovative Tech: Dual mesh coil\n\nLost Mary MT15000 Turbo Flavors:&nbsp;\n\n\nThermal Edition: Berry Burst: Experience the burst of ripe berries with a refreshing twist, igniting your taste buds with vibrant flavor.\n\n\nThermal Edition: Cherry Strazz: Indulge in the delightful fusion of sweet cherries and tangy strawberries, creating a symphony of fruity bliss.\n\n\nThermal Edition: Citrus Sunrise: Awaken your senses with the zesty sunrise of citrus fruits, offering a bright and invigorating vape experience.\n\n\nThermal Edition: Miami Mint: Cool off with the refreshing breeze of Miami Mint, a soothing blend of icy freshness that invigorates with every puff.\n\n\nThermal Edition: Strawberry Orange: Savor the harmony of luscious strawberries and juicy oranges, delivering a burst of summery sweetness with every inhale.\n\n\nThermal Edition: Summer Grape: Dive into the essence of summer with Summer Grape, a succulent blend of ripe grapes that tantalizes the palate.\n\n\nBaja Splash: Transport yourself to a tropical paradise with Baja Splash, a fusion of exotic fruits that refreshes and delights.\n\n\nBanana Cake: Indulge in the comforting sweetness of Banana Cake, a delectable dessert vape that satisfies your cravings.\n\n\nBlue Razz Ice: Chill out with the frosty blast of Blue Razz Ice, combining tangy blue raspberry with a refreshing menthol kick.\n\n\nDr. Cherry: Quench your thirst with the classic taste of Dr. Cherry, delivering the bold flavor of cherry soda in every puff.\n\n\nNana Coconut: Escape to the tropics with Nana Coconut, a creamy blend of ripe bananas and smooth coconut that transports you to paradise.\n\n\nStrawberry Kiwi: Delight in the juicy fusion of ripe strawberries and tangy kiwi, creating a harmonious balance of sweet and tart flavors.\n\n\nStrawmelon Peach: Experience the succulent blend of ripe strawberries, juicy watermelon, and luscious peach, offering a burst of summer goodness.\n\n\nWatermelon Ice: Refresh yourself with Watermelon Ice, a crisp and juicy watermelon flavor enhanced with a cooling menthol finish.\n\n\nWinter Mint: Embrace the chill of Winter Mint, a refreshing menthol vape that leaves a cool, invigorating sensation with every exhale.\n\nRocket Popsicle NEW: Blast off with a tangy burst of fruity delight.\nPeach NEW: Indulge in the sweet essence of ripe peaches.\nGrapefruit Berries NEW: A zesty fusion of grapefruit and mixed berries.\nGrape Apple NEW: Experience the juicy blend of grapes and crisp apples.\nBlueRazzDragon NEW: Conquer your cravings with the bold flavor of blue raspberry and dragon fruit.\n\nLost Mary MT15000 Turbo Wholesale:&nbsp;\nExperience the ultimate vaping sensation with Lost Mary MT15000 Turbo wholesale. Boasting exceptional power, durability, and a variety of tantalizing flavors, these disposables are a must-have for any vape shop. With 15000 puffs per device, rechargeable capabilities, and premium craftsmanship, Lost Mary MT15000 Turbo offers your customers a top-tier vaping experience. Stock up on these wholesale gems today and elevate your vape shop's offerings to new heights.\nShop Lost Mary Turbo MT15000 Retail\n\n\n\n\nLost Mary MT15000 Turbo Wholesale FAQ (Frequently Asked Questions):\n1. What is the Lost Mary MT15000 Turbo Vape Wholesale?\nThe Lost Mary MT15000 Turbo Vape is a high-capacity disposable vape with up to 15,000 puffs. It features a 5% nicotine strength, dual vaping modes (smooth mode at 11W and turbo mode at 22W), and dual mesh coil technology for enhanced flavor and vapor production.\n2. How many puffs does this vape offer?\nThe Lost Mary MTâ€¦",
    "stock_status": "Sold Out",
    "model_type": "MT15000 Turbo",
    "flavors": [
      "Berry Burst",
      "Cherry Strazz",
      "Citrus Sunrise",
      "Miami Mint",
      "Strawberry Orange",
      "Summer Grape",
      "Watermelon Ice",
      "Banana Cake",
      "Baja Splash",
      "Blue Razz Ice",
      "Dr. Cherry",
      "Nana Coconut",
      "Strawberry Kiwi",
      "Strawmelon Peach",
      "Rocket Popsicle",
      "Peach",
      "Grape Apple",
      "BlueRazzDragon",
      "Raspberry Banana",
      "Frozen White Strawberry",
      "Grapefruit Berries",
      "Winter Mint"
    ],
    "puff_count": 15000,
    "nicotine_strength": "5% (50MG)",
    "battery_capacity": null,
    "coil_type": "Dual Mesh",
    "e_liquid_capacity": "15ml"
  }
]